{"fjelstul_match_id":"M-1938-10","match_time":"17:00","managers":[{"team":"Brazil","manager":"Adhemar Pimenta","country":"Brazil","home_team":true},{"team":"Czechoslovakia","manager":"Josef Meissner","country":"Czechoslovakia","home_team":false}],"goals":[{"minute":"30'","team":"Brazil","player":"Leônidas","own_goal":false,"penalty":false,"home_team":true},{"minute":"65'","team":"Czechoslovakia","player":"Oldřich Nejedlý","own_goal":false,"penalty":true,"home_team":false}],"bookings":[],"substitutions":[],"penalty_kicks":[],"starters":[],"bench":[],"referees":[{"name":"Pál von Hertzka","country":"Hungary"}]}