{"fjelstul_match_id":"M-1970-12","goals":[{"minute":"65'","team":"Peru","player":"Teófilo Cubillas","own_goal":false,"penalty":false,"home_team":true},{"minute":"67'","team":"Peru","player":"Roberto Challe","own_goal":false,"penalty":false,"home_team":true},{"minute":"75'","team":"Peru","player":"Teófilo Cubillas","own_goal":false,"penalty":false,"home_team":true}],"bookings":[],"substitutions":[{"minute":"56'","team":"Peru","player_off":"Ramón Mifflin","player_on":"Luis Cruzado","home_team":true},{"minute":"66'","team":"Morocco","player_off":"Boujemaa Benkhrif","player_on":"Jalili Fadili","home_team":false},{"minute":"76'","team":"Peru","player_off":"Alberto Gallardo","player_on":"Oswaldo Ramírez","home_team":true},{"minute":"81'","team":"Morocco","player_off":"Said Ghandi","player_on":"Ahmed Alaoui","home_team":false}],"penalty_kicks":[],"starters":[{"number":"1","player":"Luis Rubiños","position":"goal keeper","position_code":"GK","home_team":true,"came_on":false},{"number":"3","player":"Orlando de la Torre","position":"defender","position_code":"DF","home_team":true,"came_on":false},{"number":"4","player":"Héctor Chumpitaz","position":"defender","position_code":"DF","home_team":true,"came_on":false},{"number":"5","player":"Nicolás Fuentes","position":"defender","position_code":"DF","home_team":true,"came_on":false},{"number":"6","player":"Ramón Mifflin","position":"midfielder","position_code":"MF","home_team":true,"came_on":false},{"number":"7","player":"Roberto Challe","position":"midfielder","position_code":"MF","home_team":true,"came_on":false},{"number":"9","player":"Pedro Pablo León","position":"forward","position_code":"FW","home_team":true,"came_on":false},{"number":"10","player":"Teófilo Cubillas","position":"forward","position_code":"FW","home_team":true,"came_on":false},{"number":"11","player":"Alberto Gallardo","position":"forward","position_code":"FW","home_team":true,"came_on":false},{"number":"13","player":"Pedro González","position":"defender","position_code":"DF","home_team":true,"came_on":false},{"number":"20","player":"Hugo Sotil","position":"forward","position_code":"FW","home_team":true,"came_on":false},{"number":"1","player":"Allal Ben Kassou","position":"goal keeper","position_code":"GK","home_team":false,"came_on":false},{"number":"2","player":"Abdallah Lamrani","position":"defender","position_code":"DF","home_team":false,"came_on":false},{"number":"3","player":"Boujemaa Benkhrif","position":"defender","position_code":"DF","home_team":false,"came_on":false},{"number":"4","player":"Moulay Khanousi","position":"defender","position_code":"DF","home_team":false,"came_on":false},{"number":"5","player":"Kacem Slimani","position":"defender","position_code":"DF","home_team":false,"came_on":false},{"number":"6","player":"Mohammed Mahroufi","position":"midfielder","position_code":"MF","home_team":false,"came_on":false},{"number":"7","player":"Said Ghandi","position":"midfielder","position_code":"MF","home_team":false,"came_on":false},{"number":"8","player":"Driss Bamous","position":"midfielder","position_code":"MF","home_team":false,"came_on":false},{"number":"10","player":"Mohammed El Filali","position":"midfielder","position_code":"MF","home_team":false,"came_on":false},{"number":"11","player":"Maouhoub Ghazouani","position":"forward","position_code":"FW","home_team":false,"came_on":false},{"number":"14","player":"Houmane Jarir","position":"forward","position_code":"FW","home_team":false,"came_on":false}],"bench":[{"number":"17","player":"Luis Cruzado","position":"midfielder","position_code":"MF","home_team":true,"came_on":true},{"number":"22","player":"Oswaldo Ramírez","position":"forward","position_code":"FW","home_team":true,"came_on":true},{"number":"13","player":"Jalili Fadili","position":"defender","position_code":"DF","home_team":false,"came_on":true},{"number":"17","player":"Ahmed Alaoui","position":"forward","position_code":"FW","home_team":false,"came_on":true}],"referees":[{"name":"Tofiq Bahramov","country":"Soviet Union"}]}