{"fjelstul_match_id":"M-1994-47","goals":[{"minute":"47'","team":"Germany","player":"Lothar Matthäus","own_goal":false,"penalty":true,"home_team":false},{"minute":"75'","team":"Bulgaria","player":"Hristo Stoichkov","own_goal":false,"penalty":false,"home_team":true},{"minute":"78'","team":"Bulgaria","player":"Yordan Letchkov","own_goal":false,"penalty":false,"home_team":true}],"bookings":[{"minute":"14'","team":"Germany","player":"Thomas Helmer","yellow_card":true,"red_card":false,"second_yellow_card":false},{"minute":"15'","team":"Germany","player":"Martin Wagner","yellow_card":true,"red_card":false,"second_yellow_card":false},{"minute":"22'","team":"Bulgaria","player":"Trifon Ivanov","yellow_card":true,"red_card":false,"second_yellow_card":false},{"minute":"49'","team":"Germany","player":"Thomas Häßler","yellow_card":true,"red_card":false,"second_yellow_card":false},{"minute":"50'","team":"Germany","player":"Jürgen Klinsmann","yellow_card":true,"red_card":false,"second_yellow_card":false},{"minute":"82'","team":"Bulgaria","player":"Hristo Stoichkov","yellow_card":true,"red_card":false,"second_yellow_card":false},{"minute":"85'","team":"Bulgaria","player":"Borislav Mihaylov","yellow_card":true,"red_card":false,"second_yellow_card":false},{"minute":"89'","team":"Germany","player":"Rudi Völler","yellow_card":true,"red_card":false,"second_yellow_card":false}],"substitutions":[{"minute":"59'","team":"Germany","player_off":"Martin Wagner","player_on":"Thomas Strunz","home_team":false},{"minute":"83'","team":"Germany","player_off":"Thomas Häßler","player_on":"Andreas Brehme","home_team":false},{"minute":"85'","team":"Bulgaria","player_off":"Hristo Stoichkov","player_on":"Ivaylo Yordanov","home_team":true},{"minute":"90'","team":"Bulgaria","player_off":"Emil Kostadinov","player_on":"Boncho Genchev","home_team":true}],"penalty_kicks":[],"starters":[{"number":"1","player":"Borislav Mihaylov","position":"goal keeper","position_code":"GK","home_team":true,"came_on":false},{"number":"3","player":"Trifon Ivanov","position":"defender","position_code":"DF","home_team":true,"came_on":false},{"number":"4","player":"Tsanko Tsvetanov","position":"defender","position_code":"DF","home_team":true,"came_on":false},{"number":"5","player":"Petar Hubchev","position":"defender","position_code":"DF","home_team":true,"came_on":false},{"number":"6","player":"Zlatko Yankov","position":"midfielder","position_code":"MF","home_team":true,"came_on":false},{"number":"7","player":"Emil Kostadinov","position":"forward","position_code":"FW","home_team":true,"came_on":false},{"number":"8","player":"Hristo Stoichkov","position":"forward","position_code":"FW","home_team":true,"came_on":false},{"number":"9","player":"Yordan Letchkov","position":"midfielder","position_code":"MF","home_team":true,"came_on":false},{"number":"10","player":"Nasko Sirakov","position":"midfielder","position_code":"MF","home_team":true,"came_on":false},{"number":"16","player":"Iliyan Kiryakov","position":"defender","position_code":"DF","home_team":true,"came_on":false},{"number":"20","player":"Krasimir Balakov","position":"midfielder","position_code":"MF","home_team":true,"came_on":false},{"number":"1","player":"Bodo Illgner","position":"goal keeper","position_code":"GK","home_team":false,"came_on":false},{"number":"4","player":"Jürgen Kohler","position":"defender","position_code":"DF","home_team":false,"came_on":false},{"number":"5","player":"Thomas Helmer","position":"defender","position_code":"DF","home_team":false,"came_on":false},{"number":"6","player":"Guido Buchwald","position":"defender","position_code":"DF","home_team":false,"came_on":false},{"number":"7","player":"Andreas Möller","position":"midfielder","position_code":"MF","home_team":false,"came_on":false},{"number":"8","player":"Thomas Häßler","position":"midfielder","position_code":"MF","home_team":false,"came_on":false},{"number":"10","player":"Lothar Matthäus","position":"midfielder","position_code":"MF","home_team":false,"came_on":false},{"number":"13","player":"Rudi Völler","position":"forward","position_code":"FW","home_team":false,"came_on":false},{"number":"14","player":"Thomas Berthold","position":"defender","position_code":"DF","home_team":false,"came_on":false},{"number":"17","player":"Martin Wagner","position":"midfielder","position_code":"MF","home_team":false,"came_on":false},{"number":"18","player":"Jürgen Klinsmann","position":"forward","position_code":"FW","home_team":false,"came_on":false}],"bench":[{"number":"13","player":"Ivaylo Yordanov","position":"forward","position_code":"FW","home_team":true,"came_on":true},{"number":"14","player":"Boncho Genchev","position":"forward","position_code":"FW","home_team":true,"came_on":true},{"number":"2","player":"Thomas Strunz","position":"midfielder","position_code":"MF","home_team":false,"came_on":true},{"number":"3","player":"Andreas Brehme","position":"defender","position_code":"DF","home_team":false,"came_on":true}],"referees":[{"name":"José Torres Cadena","country":"Colombia"}]}