{"fjelstul_match_id":"M-1958-32","goals":[{"minute":"2'","team":"Brazil","player":"Vavá","own_goal":false,"penalty":false,"home_team":true},{"minute":"9'","team":"France","player":"Just Fontaine","own_goal":false,"penalty":false,"home_team":false},{"minute":"39'","team":"Brazil","player":"Didi","own_goal":false,"penalty":false,"home_team":true},{"minute":"52'","team":"Brazil","player":"Pelé","own_goal":false,"penalty":false,"home_team":true},{"minute":"64'","team":"Brazil","player":"Pelé","own_goal":false,"penalty":false,"home_team":true},{"minute":"75'","team":"Brazil","player":"Pelé","own_goal":false,"penalty":false,"home_team":true},{"minute":"83'","team":"France","player":"Roger Piantoni","own_goal":false,"penalty":false,"home_team":false}],"bookings":[],"substitutions":[],"penalty_kicks":[]}